pip_api/__init__.py
pip_api/_call.py
pip_api/_hash.py
pip_api/_installed_distributions.py
pip_api/_parse_requirements.py
pip_api/_pep650.py
pip_api/_version.py
pip_api/exceptions.py
pip_api/py.typed
pip_api/_vendor/__init__.py
pip_api/_vendor/pyparsing.py
pip_api/_vendor/packaging/__about__.py
pip_api/_vendor/packaging/__init__.py
pip_api/_vendor/packaging/_manylinux.py
pip_api/_vendor/packaging/_musllinux.py
pip_api/_vendor/packaging/_structures.py
pip_api/_vendor/packaging/markers.py
pip_api/_vendor/packaging/requirements.py
pip_api/_vendor/packaging/specifiers.py
pip_api/_vendor/packaging/tags.py
pip_api/_vendor/packaging/utils.py
pip_api/_vendor/packaging/version.py
pip_api-0.0.30.dist-info/LICENSE
pip_api-0.0.30.dist-info/METADATA
pip_api-0.0.30.dist-info/WHEEL
pip_api-0.0.30.dist-info/top_level.txt
pip_api-0.0.30.dist-info/RECORD
