Metadata-Version: 2.1
Name: pip-api
Version: 0.0.30
Summary: An unofficial, importable pip API
Home-page: http://github.com/di/pip-api
Author: Dustin Ingram
Author-email: di@python.org
Classifier: License :: OSI Approved :: Apache Software License
Classifier: Programming Language :: Python :: 3 :: Only
Classifier: Programming Language :: Python :: 3
Classifier: Programming Language :: Python :: 3.7
Classifier: Programming Language :: Python :: 3.8
Classifier: Programming Language :: Python :: 3.9
Classifier: Programming Language :: Python :: 3.10
Requires-Python: >=3.7
License-File: LICENSE
